plategaio.py
plategaio-1.0.4.dist-info/licenses/LICENSE
plategaio-1.0.4.dist-info/METADATA
plategaio-1.0.4.dist-info/WHEEL
plategaio-1.0.4.dist-info/top_level.txt
plategaio-1.0.4.dist-info/RECORD
