Metadata-Version: 2.4
Name: plategaio
Version: 1.0.4
Summary: A simple and unofficial SDK for the Platega.io API.
Author-email: ploki1337 <ploki1337@gmail.com>
License: MIT License
Project-URL: Homepage, https://github.com/ploki1337/plategaio
Keywords: platega,plategaio,api,sdk,payment,async,asyncio,httpx
Classifier: Development Status :: 4 - Beta
Classifier: Programming Language :: Python :: 3
Classifier: Programming Language :: Python :: 3.8
Classifier: Programming Language :: Python :: 3.9
Classifier: Programming Language :: Python :: 3.10
Classifier: Programming Language :: Python :: 3.11
Classifier: Programming Language :: Python :: 3.12
Classifier: License :: OSI Approved :: MIT License
Classifier: Operating System :: OS Independent
Classifier: Intended Audience :: Developers
Classifier: Framework :: AsyncIO
Classifier: Topic :: Software Development :: Libraries :: Python Modules
Requires-Python: >=3.8
License-File: LICENSE
Requires-Dist: httpx>=0.27.0
Requires-Dist: pydantic>=2.7.0
Dynamic: license-file
